easypwn/__init__.py
easypwn/easycheck.py
easypwn-0.0.1.dist-info/METADATA
easypwn-0.0.1.dist-info/WHEEL
easypwn-0.0.1.dist-info/entry_points.txt
easypwn-0.0.1.dist-info/licenses/LICENSE
easypwn-0.0.1.dist-info/RECORD
