Metadata-Version: 2.4
Name: easypwn
Version: 0.0.1
Summary: Make pwn easier again
License-File: LICENSE
Requires-Dist: pwntools>=4.10.0
